<?xml version="1.0" encoding="UTF-8"?>
<MF0 version="1.1" packageUris="http://schema.mathworks.com/mf0/ci/19700101 http://schema.mathworks.com/mf0/sl_modelref_info/R2021a http://schema.mathworks.com/mf0/slexec_mm_sto/R2021a_202007071525">
  <ModelRefInfoRepo.ModelRefInfoRoot type="ModelRefInfoRepo.ModelRefInfoRoot" uuid="db12c1ad-c627-4d63-ba1d-82b125471693">
    <autoSolverStatusFlags>331</autoSolverStatusFlags>
    <childModelRefInfo type="ModelRefInfoRepo.ChildModelRefInfo" uuid="3e5c2209-14fa-4100-8046-6dcc3352c99d">
      <modelName>IncCounter</modelName>
      <modelPath>IncCounter</modelPath>
    </childModelRefInfo>
    <dataTransferInfos>AAFJTQAAAAAOAAAAOAAAAAYAAAAIAAAAAgAAAAAAAAAFAAAACAAAAAAAAAABAAAAAQAAAAAAAAAFAAQAAQAAAAEAAAAAAAAA</dataTransferInfos>
    <defaultsCMapping>{&quot;Inports&quot;:&quot;{\&quot;Name\&quot;:\&quot;Default\&quot;,\&quot;Checksum\&quot;:\&quot;Default\&quot;,\&quot;PerInstancePropertiesChecksum\&quot;:\&quot;\&quot;,\&quot;MemorySectionName\&quot;:\&quot;None\&quot;,\&quot;MemorySectionChecksum\&quot;:\&quot;None\&quot;}&quot;,&quot;Outports&quot;:&quot;{\&quot;Name\&quot;:\&quot;Default\&quot;,\&quot;Checksum\&quot;:\&quot;Default\&quot;,\&quot;PerInstancePropertiesChecksum\&quot;:\&quot;\&quot;,\&quot;MemorySectionName\&quot;:\&quot;None\&quot;,\&quot;MemorySectionChecksum\&quot;:\&quot;None\&quot;}&quot;,&quot;ParameterArguments&quot;:&quot;{\&quot;Name\&quot;:\&quot;Default\&quot;,\&quot;Checksum\&quot;:\&quot;Default\&quot;,\&quot;PerInstancePropertiesChecksum\&quot;:\&quot;\&quot;,\&quot;MemorySectionName\&quot;:\&quot;None\&quot;,\&quot;MemorySectionChecksum\&quot;:\&quot;None\&quot;}&quot;,&quot;LocalParameters&quot;:&quot;{\&quot;Name\&quot;:\&quot;Default\&quot;,\&quot;Checksum\&quot;:\&quot;Default\&quot;,\&quot;PerInstancePropertiesChecksum\&quot;:\&quot;\&quot;,\&quot;MemorySectionName\&quot;:\&quot;None\&quot;,\&quot;MemorySectionChecksum\&quot;:\&quot;None\&quot;}&quot;,&quot;GlobalParameters&quot;:&quot;{\&quot;Name\&quot;:\&quot;Default\&quot;,\&quot;Checksum\&quot;:\&quot;Default\&quot;,\&quot;PerInstancePropertiesChecksum\&quot;:\&quot;\&quot;,\&quot;MemorySectionName\&quot;:\&quot;None\&quot;,\&quot;MemorySectionChecksum\&quot;:\&quot;None\&quot;}&quot;,&quot;InternalData&quot;:&quot;{\&quot;Name\&quot;:\&quot;Default\&quot;,\&quot;Checksum\&quot;:\&quot;Default\&quot;,\&quot;PerInstancePropertiesChecksum\&quot;:\&quot;\&quot;,\&quot;MemorySectionName\&quot;:\&quot;None\&quot;,\&quot;MemorySectionChecksum\&quot;:\&quot;None\&quot;}&quot;,&quot;SharedLocalDataStores&quot;:&quot;{\&quot;Name\&quot;:\&quot;Default\&quot;,\&quot;Checksum\&quot;:\&quot;Default\&quot;,\&quot;PerInstancePropertiesChecksum\&quot;:\&quot;\&quot;,\&quot;MemorySectionName\&quot;:\&quot;None\&quot;,\&quot;MemorySectionChecksum\&quot;:\&quot;None\&quot;}&quot;,&quot;GlobalDataStores&quot;:&quot;{\&quot;Name\&quot;:\&quot;Default\&quot;,\&quot;Checksum\&quot;:\&quot;Default\&quot;,\&quot;PerInstancePropertiesChecksum\&quot;:\&quot;\&quot;,\&quot;MemorySectionName\&quot;:\&quot;None\&quot;,\&quot;MemorySectionChecksum\&quot;:\&quot;None\&quot;}&quot;,&quot;Constants&quot;:&quot;{\&quot;Name\&quot;:\&quot;Default\&quot;,\&quot;Checksum\&quot;:\&quot;Default\&quot;,\&quot;PerInstancePropertiesChecksum\&quot;:\&quot;\&quot;,\&quot;MemorySectionName\&quot;:\&quot;None\&quot;,\&quot;MemorySectionChecksum\&quot;:\&quot;None\&quot;}&quot;,&quot;DataTransfers&quot;:&quot;{\&quot;Name\&quot;:\&quot;Default\&quot;,\&quot;Checksum\&quot;:\&quot;Default\&quot;,\&quot;PerInstancePropertiesChecksum\&quot;:\&quot;\&quot;,\&quot;MemorySectionName\&quot;:\&quot;None\&quot;,\&quot;MemorySectionChecksum\&quot;:\&quot;None\&quot;}&quot;,&quot;ModelData&quot;:&quot;{\&quot;Name\&quot;:\&quot;Default\&quot;,\&quot;Checksum\&quot;:\&quot;Default\&quot;,\&quot;PerInstancePropertiesChecksum\&quot;:\&quot;\&quot;,\&quot;MemorySectionName\&quot;:\&quot;None\&quot;,\&quot;MemorySectionChecksum\&quot;:\&quot;None\&quot;}&quot;,&quot;InitializeTerminate&quot;:&quot;{\&quot;Name\&quot;:\&quot;Default\&quot;,\&quot;Checksum\&quot;:\&quot;Default\&quot;,\&quot;PerInstancePropertiesChecksum\&quot;:\&quot;\&quot;,\&quot;MemorySectionName\&quot;:\&quot;None\&quot;,\&quot;MemorySectionChecksum\&quot;:\&quot;None\&quot;}&quot;,&quot;Execution&quot;:&quot;{\&quot;Name\&quot;:\&quot;Default\&quot;,\&quot;Checksum\&quot;:\&quot;Default\&quot;,\&quot;PerInstancePropertiesChecksum\&quot;:\&quot;\&quot;,\&quot;MemorySectionName\&quot;:\&quot;None\&quot;,\&quot;MemorySectionChecksum\&quot;:\&quot;None\&quot;}&quot;,&quot;SharedUtility&quot;:&quot;{\&quot;Name\&quot;:\&quot;Default\&quot;,\&quot;Checksum\&quot;:\&quot;Default\&quot;,\&quot;PerInstancePropertiesChecksum\&quot;:\&quot;\&quot;,\&quot;MemorySectionName\&quot;:\&quot;None\&quot;,\&quot;MemorySectionChecksum\&quot;:\&quot;None\&quot;}&quot;}</defaultsCMapping>
    <fundamentalSampleTimePeriod>.2</fundamentalSampleTimePeriod>
    <hasBlockWithPeriodicDiscreteSampleTime>true</hasBlockWithPeriodicDiscreteSampleTime>
    <hasBwsAccessed>true</hasBwsAccessed>
    <hasBwsAccessedByAnyModel>true</hasBwsAccessedByAnyModel>
    <hasNonVirtualConstantTs>true</hasNonVirtualConstantTs>
    <inports type="ModelRefInfoRepo.InportInformation" uuid="3aa07f0e-bc66-4dd5-8369-2a7516018a02">
      <isNotDerivPort>true</isNotDerivPort>
      <designMax>Inf</designMax>
      <designMin>-Inf</designMin>
      <indexType>2</indexType>
      <rateInfo type="ModelRefInfoRepo.RateInfo">
        <compiled>true</compiled>
        <nonFcnCallPartitionName>D1</nonFcnCallPartitionName>
        <period>.2</period>
        <priority>40</priority>
        <rateIdx>0</rateIdx>
      </rateInfo>
      <resolvedSignalObject></resolvedSignalObject>
      <sigNameToEMVCEMap type="ModelRefInfoRepo.SigNameEMVCEInfo" uuid="ab266174-fd63-46d2-acee-bddf1a35663a"/>
    </inports>
    <isBdInSimModeForSimCodegenVariants>false</isBdInSimModeForSimCodegenVariants>
    <isInlineParamsOn>true</isInlineParamsOn>
    <isOrigInportVirtualBus>false</isOrigInportVirtualBus>
    <isOrigOutportVirtualBus>false</isOrigOutportVirtualBus>
    <loggingSaveFormat>2</loggingSaveFormat>
    <maxFreqHz>-1.0</maxFreqHz>
    <numDStateRecs>1</numDStateRecs>
    <numDataInputPorts>1</numDataInputPorts>
    <numLoggableDStateRecs>1</numLoggableDStateRecs>
    <numLoggableJacobianDStates>1</numLoggableJacobianDStates>
    <origInportBusType></origInportBusType>
    <origOutportBusOutputAsStruct>false</origOutportBusOutputAsStruct>
    <origOutportBusType></origOutportBusType>
    <outports type="ModelRefInfoRepo.OutportInformation" uuid="e44fb80a-23a5-45ca-9a8f-5bfc6442b599">
      <designMax>Inf</designMax>
      <designMin>-Inf</designMin>
      <rateInfo type="ModelRefInfoRepo.RateInfo">
        <compiled>true</compiled>
        <nonFcnCallPartitionName>D1</nonFcnCallPartitionName>
        <period>.2</period>
        <priority>40</priority>
        <rateIdx>0</rateIdx>
      </rateInfo>
      <resolvedSignalObject></resolvedSignalObject>
      <sigNameToEMVCEMap type="ModelRefInfoRepo.SigNameEMVCEInfo" uuid="1070bfb4-620d-441b-ac6e-e21f4d0d4420"/>
    </outports>
    <removeResetFunc>true</removeResetFunc>
    <runtimeNonFcnCallRateInfos type="ModelRefInfoRepo.RateInfo">
      <compiled>true</compiled>
      <nonFcnCallPartitionName>D1</nonFcnCallPartitionName>
      <period>.2</period>
      <priority>40</priority>
      <rateIdx>0</rateIdx>
    </runtimeNonFcnCallRateInfos>
    <sampleTimeInheritanceRule>1</sampleTimeInheritanceRule>
    <timingAndTaskingRegistry>&lt;?xml version=&quot;1.0&quot;?&gt;
&lt;slexec_sto version=&quot;1.1&quot; packageUris=&quot;http://schema.mathworks.com/mf0/slexec_mm_sto/R2021a_202007071525&quot;&gt;
  &lt;sto.Registry type=&quot;sto.Registry&quot; uuid=&quot;5bdbe022-aaf7-419a-9943-5189f430f44b&quot;&gt;
    &lt;clocks type=&quot;sto.Timer&quot; uuid=&quot;8bfe4742-55f3-46e5-baef-8506e0a59264&quot;&gt;
      &lt;computedFundamentalDiscretePeriod&gt;.2&lt;/computedFundamentalDiscretePeriod&gt;
      &lt;resolution&gt;.2&lt;/resolution&gt;
      &lt;clockTickConstraint&gt;PeriodicWithFixedResolution&lt;/clockTickConstraint&gt;
      &lt;specifiedTaskingMode&gt;ClassicMultiTasking&lt;/specifiedTaskingMode&gt;
      &lt;timeAdvanceMode&gt;FixedStep&lt;/timeAdvanceMode&gt;
      &lt;clockDomain type=&quot;sto.ClockDomain&quot; uuid=&quot;3b4b7aef-5277-4362-a933-b91b010d0ce4&quot;&gt;
        &lt;baseTaskID&gt;_task0&lt;/baseTaskID&gt;
        &lt;rates type=&quot;sto.Rate&quot; uuid=&quot;03617c06-ef20-4c27-89c0-fc8a3609dce3&quot;/&gt;
        &lt;rootTaskHierarchyElements type=&quot;sto.Task&quot; uuid=&quot;e88298a7-9a31-49f7-ab4e-284bebd1bec4&quot;&gt;
          &lt;isExecutable&gt;true&lt;/isExecutable&gt;
          &lt;orderIndex&gt;1&lt;/orderIndex&gt;
          &lt;rates type=&quot;sto.Rate&quot; uuid=&quot;03617c06-ef20-4c27-89c0-fc8a3609dce3&quot;&gt;
            &lt;annotation&gt;D1&lt;/annotation&gt;
            &lt;colorIndex&gt;2&lt;/colorIndex&gt;
            &lt;description&gt;Discrete 1&lt;/description&gt;
            &lt;eventSourceType&gt;UNSPECIFIED_EVENT_SOURCE&lt;/eventSourceType&gt;
            &lt;registry type=&quot;sto.Registry&quot; uuid=&quot;5bdbe022-aaf7-419a-9943-5189f430f44b&quot;/&gt;
            &lt;taskId&gt;_task0&lt;/taskId&gt;
            &lt;rateSpec type=&quot;sto.RateSpec&quot; uuid=&quot;e0d2218d-8366-445e-8378-e87f393f6e87&quot;&gt;
              &lt;period&gt;.2&lt;/period&gt;
              &lt;rateType&gt;ClassicPeriodicDiscrete&lt;/rateType&gt;
            &lt;/rateSpec&gt;
          &lt;/rates&gt;
          &lt;elementType&gt;Task&lt;/elementType&gt;
          &lt;identifier&gt;_task0&lt;/identifier&gt;
          &lt;priority&gt;40&lt;/priority&gt;
        &lt;/rootTaskHierarchyElements&gt;
      &lt;/clockDomain&gt;
    &lt;/clocks&gt;
    &lt;clocks type=&quot;sto.Event&quot; uuid=&quot;34fc85b1-577a-47fe-93fb-be308811952b&quot;&gt;
      &lt;clientId&gt;NonTunableParameterChangeEvent&lt;/clientId&gt;
      &lt;eventType&gt;UNSPECIFIED_EVENT_SOURCE&lt;/eventType&gt;
      &lt;cNum&gt;2&lt;/cNum&gt;
      &lt;clockType&gt;Event&lt;/clockType&gt;
      &lt;identifier&gt;NonTunableParameterChangeEvent&lt;/identifier&gt;
      &lt;specifiedTaskingMode&gt;ExplicitTasking&lt;/specifiedTaskingMode&gt;
      &lt;timeAdvanceMode&gt;None&lt;/timeAdvanceMode&gt;
      &lt;clockDomain type=&quot;sto.ClockDomain&quot; uuid=&quot;e60e197b-14df-4f37-b62a-bed2ddc34861&quot;/&gt;
    &lt;/clocks&gt;
    &lt;clocks type=&quot;sto.Event&quot; uuid=&quot;e37926b8-d6be-4c0f-8108-cdb9a7829b78&quot;&gt;
      &lt;clientId&gt;ParameterChangeEvent&lt;/clientId&gt;
      &lt;eventType&gt;PARAMETER_CHANGE_EVENT&lt;/eventType&gt;
      &lt;cNum&gt;1&lt;/cNum&gt;
      &lt;clockType&gt;Event&lt;/clockType&gt;
      &lt;identifier&gt;ParameterChangeEvent&lt;/identifier&gt;
      &lt;specifiedTaskingMode&gt;ExplicitTasking&lt;/specifiedTaskingMode&gt;
      &lt;timeAdvanceMode&gt;None&lt;/timeAdvanceMode&gt;
      &lt;clockDomain type=&quot;sto.ClockDomain&quot; uuid=&quot;5406d191-796e-470a-a868-cdc297847528&quot;&gt;
        &lt;rates type=&quot;sto.Rate&quot; uuid=&quot;f612c0ee-14b4-4a0e-a3e1-b787016ee57b&quot;/&gt;
        &lt;rootTaskHierarchyElements type=&quot;sto.Task&quot; uuid=&quot;19a3fe6a-7f83-4bd4-967c-8209b465d1ca&quot;&gt;
          &lt;isExplicit&gt;true&lt;/isExplicit&gt;
          &lt;rates type=&quot;sto.Rate&quot; uuid=&quot;f612c0ee-14b4-4a0e-a3e1-b787016ee57b&quot;&gt;
            &lt;eventSourceType&gt;PARAMETER_CHANGE_EVENT&lt;/eventSourceType&gt;
            &lt;rateIDX&gt;-1&lt;/rateIDX&gt;
            &lt;registry type=&quot;sto.Registry&quot; uuid=&quot;5bdbe022-aaf7-419a-9943-5189f430f44b&quot;/&gt;
            &lt;stringID&gt;ParameterChangeEvent&lt;/stringID&gt;
            &lt;taskId&gt;ModelWideParameterChangeEvent&lt;/taskId&gt;
            &lt;useForExecution&gt;NotForExecution&lt;/useForExecution&gt;
            &lt;rateSpec type=&quot;sto.RateSpec&quot; uuid=&quot;8b062ce4-9a5d-4012-b606-658466d8b1c6&quot;&gt;
              &lt;period&gt;Inf&lt;/period&gt;
              &lt;rateType&gt;ModelWideParameterChangeEvent&lt;/rateType&gt;
            &lt;/rateSpec&gt;
          &lt;/rates&gt;
          &lt;tNum&gt;1&lt;/tNum&gt;
          &lt;elementType&gt;Task&lt;/elementType&gt;
          &lt;identifier&gt;ModelWideParameterChangeEvent&lt;/identifier&gt;
          &lt;priority&gt;-1&lt;/priority&gt;
          &lt;schedulingClockID&gt;ParameterChangeEvent&lt;/schedulingClockID&gt;
        &lt;/rootTaskHierarchyElements&gt;
      &lt;/clockDomain&gt;
    &lt;/clocks&gt;
    &lt;executionSpec&gt;Undetermined&lt;/executionSpec&gt;
    &lt;taskDependencyGraph type=&quot;sto.SerializedTaskConnectionList&quot; uuid=&quot;4a74b968-ab3e-472c-bdeb-a34eb64237b0&quot;&gt;
      &lt;taskIdentifier&gt;_task0&lt;/taskIdentifier&gt;
    &lt;/taskDependencyGraph&gt;
    &lt;taskDependencyGraph type=&quot;sto.SerializedTaskConnectionList&quot; uuid=&quot;31fd12df-6d9d-470e-b999-d8e27bd8f87e&quot;&gt;
      &lt;clockIdentifier&gt;ParameterChangeEvent&lt;/clockIdentifier&gt;
      &lt;taskIdentifier&gt;ModelWideParameterChangeEvent&lt;/taskIdentifier&gt;
    &lt;/taskDependencyGraph&gt;
    &lt;taskPriorityDirection&gt;HighNumberLast&lt;/taskPriorityDirection&gt;
    &lt;taskingMode&gt;ClassicMultiTasking&lt;/taskingMode&gt;
    &lt;tasks type=&quot;sto.Task&quot; uuid=&quot;e88298a7-9a31-49f7-ab4e-284bebd1bec4&quot;/&gt;
    &lt;tasks type=&quot;sto.Task&quot; uuid=&quot;19a3fe6a-7f83-4bd4-967c-8209b465d1ca&quot;/&gt;
    &lt;timeAdvanceMode&gt;FixedStep&lt;/timeAdvanceMode&gt;
  &lt;/sto.Registry&gt;
&lt;/slexec_sto&gt;</timingAndTaskingRegistry>
    <FMUBlockMap type="ModelRefInfoRepo.FMUBlockInfo" uuid="2ae43c53-3a1e-4e30-96ee-24605753ae69"/>
    <codeGenInfo type="ModelRefInfoRepo.CodeGenInformation" uuid="4f6123bd-a3a5-4a4a-a190-915782984214"/>
    <configSettingsForConsistencyChecks type="ModelRefInfoRepo.ConfigSettingsForConsistencyChecks" uuid="39b8d05f-4cfb-4347-ab82-20727eca9159">
      <fixedStepSize>.2</fixedStepSize>
      <frameDiagnosticSetting>2</frameDiagnosticSetting>
      <hasHybridSampleTime>true</hasHybridSampleTime>
      <optimizedInitCode>true</optimizedInitCode>
      <signalLoggingSaveFormat>2</signalLoggingSaveFormat>
      <simSIMDOptimization>1</simSIMDOptimization>
      <solverName>FixedStepDiscrete</solverName>
      <solverType>SOLVER_TYPE_FIXEDSTEP</solverType>
      <hardwareSettings type="ModelRefInfoRepo.HardwareSettings" uuid="253b9d2d-ac70-4d76-b4a9-caf777109658">
        <prodBitPerChar>8</prodBitPerChar>
        <prodBitPerDouble>64</prodBitPerDouble>
        <prodBitPerFloat>32</prodBitPerFloat>
        <prodBitPerInt>32</prodBitPerInt>
        <prodBitPerLong>32</prodBitPerLong>
        <prodBitPerLongLong>64</prodBitPerLongLong>
        <prodBitPerPointer>64</prodBitPerPointer>
        <prodBitPerPtrDiffT>64</prodBitPerPtrDiffT>
        <prodBitPerShort>16</prodBitPerShort>
        <prodBitPerSizeT>64</prodBitPerSizeT>
        <prodEndianess>1</prodEndianess>
        <prodShiftRight>true</prodShiftRight>
        <prodWordSize>64</prodWordSize>
      </hardwareSettings>
    </configSettingsForConsistencyChecks>
    <controllableInputRatesMap type="ModelRefInfoRepo.VarTsUIDMap" uuid="c9919c82-42b2-485e-ba6a-4af8c273f2ce"/>
    <controllableOutputRatesMap type="ModelRefInfoRepo.VarTsUIDMap" uuid="d956caac-0149-4e2c-ab17-db45da5f205e"/>
    <dataPortGroup type="ModelRefInfoRepo.DataPortGroup" uuid="71a5f549-71a5-461a-b7f0-e29597eb7795">
      <compDataInputPorts>0</compDataInputPorts>
      <compDataOutputPorts>0</compDataOutputPorts>
      <dataInputPorts>0</dataInputPorts>
      <dataOutputPorts>0</dataOutputPorts>
    </dataPortGroup>
    <expFcnUnconnectedDataPortGroup type="ModelRefInfoRepo.DataPortGroup" uuid="1348f8c3-b235-47ac-a0f7-73af0d1bee84"/>
    <interfaceParameterInfo type="ModelRefInfoRepo.InterfaceParameterInfo" uuid="f01f3060-332a-4077-b25e-f2101a9c5e62"/>
    <messageInfo type="ModelRefInfoRepo.MessageInformation" uuid="ef06319d-abc3-46fa-bdca-ba88b994c643"/>
    <methodInfo type="ModelRefInfoRepo.MethodExistenceInfo" uuid="bcbb0276-e387-4f1d-b7ed-155c5c62b1c4">
      <hasSystemInitializeMethod>true</hasSystemInitializeMethod>
      <hasSystemResetMethod>true</hasSystemResetMethod>
      <hasTerminateMethod>true</hasTerminateMethod>
      <hasUpdateMethod>true</hasUpdateMethod>
    </methodInfo>
    <periodicEventPortUnsupportedBlockInfo type="ModelRefInfoRepo.PeriodicEventPortUnsupportedBlockInfo" uuid="ae4fd1bd-587b-4f37-9cc6-b2124194998e"/>
    <portGroupsRequireSameRate type="ModelRefInfoRepo.PortGroupsRequireSameRate" uuid="58fb316c-fa24-4715-b84d-0afdd6368ca6">
      <DSMPortGroups type="ModelRefInfoRepo.NameToPortGroupIdxVectMap" uuid="68731b8f-0ffd-4abe-b256-84a6dfa2ee33"/>
      <GlobalDSMPortGroups type="ModelRefInfoRepo.NameToPortGroupIdxVectMap" uuid="e66df4af-4d05-459e-9362-91d488d805d5"/>
      <mergedPortGroups type="ModelRefInfoRepo.NameToPortGroupIdxVectMap" uuid="d0686aec-da00-486d-9643-654e8362e02b"/>
    </portGroupsRequireSameRate>
    <rateBasedMdlGlobalDSMRateSpec type="ModelRefInfoRepo.GlobalDSMRateSpecMap" uuid="cea2e4c3-4b4f-4ef8-ab3a-f483049636c2"/>
    <rateSpecOfGlobalDSMAccessedByDescExpFcnMdlMap type="ModelRefInfoRepo.GlobalDSMRateSpecMap" uuid="73ff8ec5-5535-481a-a643-2221537d62f4"/>
    <rootBlockDiagramInterface type="ci.Model" uuid="345bd6f3-04d3-43aa-9a8d-19a41b78adfe">
      <p_RootComponentInterface type="ci.ComponentInterface" uuid="e7c0dd22-97e3-48ca-afdc-bf522737183e">
        <p_InputPorts type="ci.SignalInterface" uuid="5f8e12b0-7917-4c63-af9c-a4359bb227e2">
          <p_ComputedNumericDimensions>1.0</p_ComputedNumericDimensions>
          <p_ComputedSampleTime>.2</p_ComputedSampleTime>
          <p_ComputedSampleTime>0.0</p_ComputedSampleTime>
        </p_InputPorts>
        <p_Name>IncCounter</p_Name>
        <p_OutputPorts type="ci.SignalInterface" uuid="68b20134-b5d9-4920-bc3f-efb62d5c15b4">
          <p_ComputedNumericDimensions>1.0</p_ComputedNumericDimensions>
          <p_ComputedSampleTime>.2</p_ComputedSampleTime>
          <p_ComputedSampleTime>0.0</p_ComputedSampleTime>
        </p_OutputPorts>
        <p_Type>ROOT</p_Type>
      </p_RootComponentInterface>
    </rootBlockDiagramInterface>
    <simulinkFunctions type="ModelRefInfoRepo.SimulinkFunctions" uuid="0064c365-ef92-4d9f-a394-8c3ab504f8fb">
      <compSimulinkFunctionCatalog></compSimulinkFunctionCatalog>
    </simulinkFunctions>
    <stateWriterToOwnerMap type="ModelRefInfoRepo.StateWriterInfo" uuid="23aef374-41b0-4459-bacd-106b0bdf70aa"/>
    <stoClientDataRegistry type="sto.ClientDataRegistry" uuid="4c726ca8-903b-47a1-94c2-fa360902737b">
      <dataSets type="sto.ClientClockNamedDataSet" uuid="8b06fafe-3503-4167-b5ec-4a5a72568a09">
        <tag>sltpEvents</tag>
      </dataSets>
      <dataSets type="sto.ClientTaskHierarchyElementNamedDataSet" uuid="f9968da1-95a3-4db4-8dbf-28ddae410fe1">
        <tag>sltpTaskGroups</tag>
      </dataSets>
      <dataSets type="sto.ClientTaskHierarchyElementNamedDataSet" uuid="aee74e7e-6511-4547-bfc5-4d59a9ccbd17">
        <dSet type="ModelRefInfoRepo.SltpTaskData" uuid="89e4582c-7cd8-4ae9-b569-7dcb5876838d"/>
        <tSet type="ModelRefInfoRepo.SltpTaskData" uuid="89e4582c-7cd8-4ae9-b569-7dcb5876838d">
          <dataName>D1</dataName>
          <linkedSet type="sto.ClientTaskHierarchyElementNamedDataSet" uuid="aee74e7e-6511-4547-bfc5-4d59a9ccbd17"/>
          <id type="sto.TaskHierarchyElementId">
            <id>_task0</id>
          </id>
        </tSet>
        <tag>sltpTasks</tag>
      </dataSets>
    </stoClientDataRegistry>
    <varTsUIDMap type="ModelRefInfoRepo.VarTsUIDMap" uuid="7e6cccaa-56f2-4a62-9633-9080e9c5e5bd"/>
  </ModelRefInfoRepo.ModelRefInfoRoot>
</MF0>